Metadata-Version: 1.0
Name: twodogstools
Version: 0.0.0
Summary: pangjinfeng private tools
Home-page: UNKNOWN
Author: pangjinfeng
Author-email: 1056808138@qq.com
License: UNKNOWN
Platform: UNKNOWN
